[
    {
        "cals": 472.0,
        "fat": 17.5,
        "carb": 68.69,
        "prot": 10.0,
        "brand": "Ver M\u00e1s"
    },
    {
        "cals": 510.0,
        "fat": 26.0,
        "carb": 52.0,
        "prot": 14.0,
        "brand": "Hacendado"
    },
    {
        "cals": 513.0,
        "fat": 26.6,
        "carb": 54.5,
        "prot": 11.6,
        "brand": "Hacendado"
    },
    {
        "cals": 471.0,
        "fat": 23.0,
        "carb": 46.0,
        "prot": 14.0,
        "brand": "Carrefour"
    },
    {
        "cals": 522.0,
        "fat": 33.7,
        "carb": 47.4,
        "prot": 15.5,
        "brand": "Ver M\u00e1s"
    }
]